{
  "bank_code": "ECB",
  "snapshot_at": "2026-07-20T23:06:25+00:00",
  "methodology_version": "1.2.0",
  "estimation_basis": "spot-anchored \u2014 forward odds unavailable",
  "rows": [
    {
      "meeting_date": "2026-06-11",
      "outcome_label": "-50bp",
      "outcome_delta_bps": -50,
      "probability": 0.0,
      "post_meeting_rate": 1.75
    },
    {
      "meeting_date": "2026-06-11",
      "outcome_label": "-25bp",
      "outcome_delta_bps": -25,
      "probability": 0.0,
      "post_meeting_rate": 2.0
    },
    {
      "meeting_date": "2026-06-11",
      "outcome_label": "Hold",
      "outcome_delta_bps": 0,
      "probability": 1.0,
      "post_meeting_rate": 2.25
    },
    {
      "meeting_date": "2026-06-11",
      "outcome_label": "+25bp",
      "outcome_delta_bps": 25,
      "probability": 0.0,
      "post_meeting_rate": 2.5
    },
    {
      "meeting_date": "2026-06-11",
      "outcome_label": "+50bp",
      "outcome_delta_bps": 50,
      "probability": 0.0,
      "post_meeting_rate": 2.75
    },
    {
      "meeting_date": "2026-07-23",
      "outcome_label": "-50bp",
      "outcome_delta_bps": -50,
      "probability": 0.0,
      "post_meeting_rate": 1.75
    },
    {
      "meeting_date": "2026-07-23",
      "outcome_label": "-25bp",
      "outcome_delta_bps": -25,
      "probability": 0.0,
      "post_meeting_rate": 2.0
    },
    {
      "meeting_date": "2026-07-23",
      "outcome_label": "Hold",
      "outcome_delta_bps": 0,
      "probability": 1.0,
      "post_meeting_rate": 2.25
    },
    {
      "meeting_date": "2026-07-23",
      "outcome_label": "+25bp",
      "outcome_delta_bps": 25,
      "probability": 0.0,
      "post_meeting_rate": 2.5
    },
    {
      "meeting_date": "2026-07-23",
      "outcome_label": "+50bp",
      "outcome_delta_bps": 50,
      "probability": 0.0,
      "post_meeting_rate": 2.75
    },
    {
      "meeting_date": "2026-09-10",
      "outcome_label": "-50bp",
      "outcome_delta_bps": -50,
      "probability": 0.0,
      "post_meeting_rate": 1.75
    },
    {
      "meeting_date": "2026-09-10",
      "outcome_label": "-25bp",
      "outcome_delta_bps": -25,
      "probability": 0.0,
      "post_meeting_rate": 2.0
    },
    {
      "meeting_date": "2026-09-10",
      "outcome_label": "Hold",
      "outcome_delta_bps": 0,
      "probability": 1.0,
      "post_meeting_rate": 2.25
    },
    {
      "meeting_date": "2026-09-10",
      "outcome_label": "+25bp",
      "outcome_delta_bps": 25,
      "probability": 0.0,
      "post_meeting_rate": 2.5
    },
    {
      "meeting_date": "2026-09-10",
      "outcome_label": "+50bp",
      "outcome_delta_bps": 50,
      "probability": 0.0,
      "post_meeting_rate": 2.75
    },
    {
      "meeting_date": "2026-12-17",
      "outcome_label": "-50bp",
      "outcome_delta_bps": -50,
      "probability": 0.0,
      "post_meeting_rate": 1.75
    },
    {
      "meeting_date": "2026-12-17",
      "outcome_label": "-25bp",
      "outcome_delta_bps": -25,
      "probability": 0.0,
      "post_meeting_rate": 2.0
    },
    {
      "meeting_date": "2026-12-17",
      "outcome_label": "Hold",
      "outcome_delta_bps": 0,
      "probability": 1.0,
      "post_meeting_rate": 2.25
    },
    {
      "meeting_date": "2026-12-17",
      "outcome_label": "+25bp",
      "outcome_delta_bps": 25,
      "probability": 0.0,
      "post_meeting_rate": 2.5
    },
    {
      "meeting_date": "2026-12-17",
      "outcome_label": "+50bp",
      "outcome_delta_bps": 50,
      "probability": 0.0,
      "post_meeting_rate": 2.75
    }
  ]
}
